{"folders": ["lcls-twincat-motion", "master", "v1.4.3", "v1.4.4", "v1.5.0", "v1.6.0"], "default-branch": "master", "labels": {"lcls-twincat-motion": "lcls-twincat-motion", "master": "master", "v1.4.3": "v1.4.3", "v1.4.4": "v1.4.4", "v1.5.0": "v1.5.0", "v1.6.0": "v1.6.0 (latest)"}, "versions": ["master", "v1.6.0", "v1.5.0", "v1.4.4", "v1.4.3", "lcls-twincat-motion"], "warnings": {"lcls-twincat-motion": ["unreleased"], "master": ["unreleased"], "v1.4.3": ["outdated"], "v1.4.4": ["outdated"], "v1.5.0": ["outdated"], "v1.6.0": []}, "latest": "v1.6.0", "downloads": {"lcls-twincat-motion": [], "master": [], "v1.4.3": [], "v1.4.4": [], "v1.5.0": [], "v1.6.0": []}}